affectivemachine/__init__.py
affectivemachine/emotion.py
affectivemachine-0.1.0.dist-info/LICENSE
affectivemachine-0.1.0.dist-info/METADATA
affectivemachine-0.1.0.dist-info/WHEEL
affectivemachine-0.1.0.dist-info/top_level.txt
affectivemachine-0.1.0.dist-info/RECORD
