Metadata-Version: 2.1
Name: affectivemachine
Version: 0.1.0
Summary: An affective computing toolkit
Author-email: Wang Zuo <u3008567@connect.hku.hk>
License: Apache License
Project-URL: homepage, https://github.com/wangzuo/affectivemachine
Project-URL: source, https://github.com/wangzuo/affectivemachine
Keywords: affective,emotion
Classifier: Programming Language :: Python
Classifier: Programming Language :: Python :: 3
Requires-Python: >=3.9
License-File: LICENSE
